{
    "allowed_users": {
        "1190003563489939568": {
            "uuid": "",
            "auto_login": false,
            "expiry": "permanent"
        },
        "515959443306053675": {
            "uuid": "",
            "auto_login": false,
            "expiry": "permanent"
        },
        "954082391385854032": {
            "uuid": "",
            "auto_login": false,
            "expiry": "permanent"
        },
        "1193247117662228541": {
            "uuid": "",
            "auto_login": false,
            "expiry": "permanent"
        },
        "1177124441352830976": {
            "uuid": "",
            "auto_login": false,
            "expiry": "permanent"
        },
        "1276837903993016343": {
            "uuid": "",
            "auto_login": false,
            "expiry": "permanent"
        },
        "1223359053544296448": {
            "uuid": "",
            "auto_login": false,
            "expiry": "permanent"
        },
        "254577507964026880": {
            "uuid": "",
            "auto_login": false,
            "expiry": "permanent"
        },
        "884311745412349972": {
            "uuid": "",
            "auto_login": false,
            "expiry": "permanent"
        },
        "1108269252995207219": {
            "uuid": "",
            "auto_login": false,
            "expiry": "permanent"
        },
        "952275078098350100": {
            "uuid": "",
            "auto_login": false,
            "expiry": "permanent"
        },
        "752593667977510963": {
            "uuid": "",
            "auto_login": false,
            "expiry": "permanent"
        },
        "1132965592333295696": {
            "uuid": "",
            "auto_login": false,
            "expiry": "permanent"
        },
        "1277177990073155616": {
            "uuid": "",
            "auto_login": false,
            "expiry": "permanent"
        },
        "1150825253040295986": {
            "uuid": "",
            "auto_login": false,
            "expiry": "permanent"
        },
        "790842912207274045": {
            "uuid": "",
            "auto_login": false,
            "expiry": "permanent"
        },
        "1159168009701695639": {
            "uuid": "",
            "auto_login": false,
            "expiry": "permanent"
        },
        "1288864629602390078": {
            "uuid": "",
            "auto_login": false,
            "expiry": "permanent"
        },
        "945410853111480421": {
            "uuid": "",
            "auto_login": false,
            "expiry": "permanent"
        },
        "936972534572781608": {
            "uuid": "",
            "auto_login": false,
            "expiry": "permanent"
        },
        "1246843560725188718": {
            "uuid": "",
            "auto_login": false,
            "expiry": "permanent"
        },
        "1220536691492786198": {
            "uuid": "",
            "auto_login": false,
            "expiry": "permanent"
        },
        "1158085809400975411": {
            "uuid": "08ab246d-dc9c-49aa-a811-36c554ea7b3d",
            "expiry": "2025-04-30T23:15:20.404009+00:00",
            "added_by": 1158085809400975411,
            "timestamp": "2025-03-31T23:15:20.404065+00:00"
        },
        "1336489586276175902": {
            "uuid": "ceb3a895-093c-46fb-85f4-89a83b01a477",
            "expiry": "2025-06-09T23:21:52.008013+00:00",
            "added_by": 1158085809400975411,
            "timestamp": "2025-03-31T23:21:52.008079+00:00"
        },
        "727281225982803972": {
            "uuid": "a6614f31-b7f1-487a-8d4b-26144c0920a9",
            "expiry": "permanent",
            "added_by": 1158085809400975411,
            "timestamp": "2025-03-31T23:22:57.039602+00:00"
        }
    }
}